python_spin
