Metadata-Version: 1.2
Name: python-spin
Version: 2020.2.6.328
Summary: a small utility to assist in setting usage modes of laptop-tablet devices
Home-page: https://github.com/wdbm/spin
Author: Will Breaden Madden
Author-email: wbm@protonmail.ch
License: GPLv3
Platform: UNKNOWN
Requires-Python: >=3.6
